{
  "project_info": {
    "project_number": "411859961693",
    "project_id": "buzztalk-31b21",
    "storage_bucket": "buzztalk-31b21.appspot.com"
  },
  "client": [
    {
      "client_info": {
        "mobilesdk_app_id": "1:411859961693:android:02a5c70efa30f501d08ab4",
        "android_client_info": {
          "package_name": "com.buzztalk.app"
        }
      },
      "oauth_client": [],
      "api_key": [
        {
          "current_key": "AIzaSyDa3XY4B0QEGxjVXIvPQqOrMJgnX7ZuVIc"
        }
      ],
      "services": {
        "appinvite_service": {
          "other_platform_oauth_client": []
        }
      }
    }
  ],
  "configuration_version": "1"
}